CHANGES.txt
CONTRIBUTORS.txt
LICENSE
MANIFEST.in
README.rst
setup.py
src/rebecca/__init__.py
src/rebecca.menu.egg-info/PKG-INFO
src/rebecca.menu.egg-info/SOURCES.txt
src/rebecca.menu.egg-info/dependency_links.txt
src/rebecca.menu.egg-info/namespace_packages.txt
src/rebecca.menu.egg-info/not-zip-safe
src/rebecca.menu.egg-info/requires.txt
src/rebecca.menu.egg-info/top_level.txt
src/rebecca/menu/__init__.py
src/rebecca/menu/interfaces.py